mcvoronoi/__init__.py
mcvoronoi-0.0.3.dist-info/LICENSE
mcvoronoi-0.0.3.dist-info/METADATA
mcvoronoi-0.0.3.dist-info/WHEEL
mcvoronoi-0.0.3.dist-info/top_level.txt
mcvoronoi-0.0.3.dist-info/RECORD
