Metadata-Version: 2.1
Name: mcvoronoi
Version: 0.0.3
Summary: mcvoronoi package
Home-page: https://github.com/abcnishant007/mcvoronoi
Author: Kusum Kumari
Author-email: kusum.kumarisjce@gmail.com
License: UNKNOWN
Platform: UNKNOWN
Classifier: Programming Language :: Python :: 3
Classifier: License :: OSI Approved :: MIT License
Classifier: Operating System :: OS Independent
Requires-Python: >=3.6
